{"product_id": "5568657", "product_title": "Whisper Cotton Crewneck T-Shirt", "product_brand": "MADEWELL", "product_color": "selected Pearl Ivory color", "product_description": "It's no secret, Madewell's best-selling crewneck T-shirt is the kind of forever favorite you'll want in every color.", "product_details_and_care": "It's no secret, Madewell's best-selling crewneck T-shirt is the kind of forever favorite you'll want in every color. Fashioned of light and airy slub cotton, this retro-striped T-shirt is live-in-it soft and perfectly draped\u2014one to tell your friends about, in other words.\n25 1/2\" length (size Medium)\nCrewneck\nShort sleeves\n100% cotton\nMachine wash, tumble dry\nImported\nt.b.d.\nItem #6030928", "product_size_info": "\nTrue to size.\nXXS=000, XS=00-0, S=2-4, M=6-8, L=10-12, XL=14-16, XXL=18 (16W).", "product_group": []}