{"product_id": "5622968", "product_title": "Davis Friendship Bracelet", "product_brand": "KENDRA SCOTT", "product_color": "selected Gold Ivory Mop color", "product_description": "A large, faceted bauble brings pretty sparkle to this woven friendship-style bracelet.", "product_details_and_care": "A large, faceted bauble brings pretty sparkle to this woven friendship-style bracelet.\nAdjusts up to 9\" inner circumference; 1/2\" pendant diameter\nAdjustable slide closure\nTextile/14k-gold plate or rhodium plate/amazonite, mother-of-pearl or glass\nImported\nItem #6068679", "product_size_info": "\nAdjustable up to 9\" inner circumference", "product_group": []}