{"product_id": "5244145", "product_title": "Hazel Woven Rattan Circle Bag", "product_brand": "MALI + LILI", "product_color": "", "product_description": "", "product_details_and_care": "Go from your local farmers' market to an alfresco brunch with the girls with this compact bag featuring earthy rattan woven into a chic round silhouette.\nMagnetic snap-tab closure\nAdjustable shoulder strap\nInterior wall pocket\nStriped lining\nRattan with PETA-certified vegan leather trim\nImported\nItem #5823536", "product_size_info": "\n7\"W x 7\"H x 3\"D. (Interior capacity: small.)\n18\" \u2013 19\" strap drop.\n.5 lb.", "product_group": []}