{"product_id": "5159250", "product_title": "Coronado Denim Romper", "product_brand": "SANCTUARY", "product_color": "", "product_description": "", "product_details_and_care": "The of-the-moment boilersuit is turned into this leg-freeing romper of lightweight, moisture-wicking stretch denim with classic utility details.\nFront button closure\nSpread collar\nThree-quarter sleeves with two-button cuffs\nButton-flap chest pockets; front and back patch pockets\nAdjustable button side tabs\nTopstitched cuffed hems\n71% cotton, 27% Sorbtek\u00ae polyester, 2% elastane\nMachine wash, tumble dry\nImported\nPoint of View\nItem #5769532", "product_size_info": "\nTrue to size.\nRegular & Petite (P): XXS=00-0, XS=2-4, S=4-6, M=8-10, L=12-14, XL=16, XXL=18 (14W).", "product_group": []}