{"product_id": "5527324", "product_title": "Gigli Platform Sandal", "product_brand": "MARC FISHER LTD", "product_color": "selected Gold/ Luggage Leather color", "product_description": "Braided trim accentuates the platform sole of this rustic yet refined ankle-strap sandal.", "product_details_and_care": "Braided trim accentuates the platform sole of this rustic yet refined ankle-strap sandal.\n3 1/4\" heel; 2\" platform\nAdjustable ankle strap with buckle closure\nLeather upper/synthetic lining and sole\nImported\nWomen's Shoes\nItem #6003551", "product_size_info": "\nTrue to size.", "product_group": []}